odoo/addons/intrastat_product/README.rst
odoo/addons/intrastat_product/__init__.py
odoo/addons/intrastat_product/__manifest__.py
odoo/addons/intrastat_product/data/intrastat_transport_mode.xml
odoo/addons/intrastat_product/data/intrastat_unit.xml
odoo/addons/intrastat_product/demo/intrastat_demo.xml
odoo/addons/intrastat_product/i18n/es.po
odoo/addons/intrastat_product/i18n/fr.po
odoo/addons/intrastat_product/i18n/intrastat_product.pot
odoo/addons/intrastat_product/migrations/13.0.1.0.3/noupdate_changes.xml
odoo/addons/intrastat_product/migrations/13.0.1.0.3/post-migration.py
odoo/addons/intrastat_product/migrations/13.0.1.0.3/pre-migration.py
odoo/addons/intrastat_product/models/__init__.py
odoo/addons/intrastat_product/models/account_move.py
odoo/addons/intrastat_product/models/hs_code.py
odoo/addons/intrastat_product/models/intrastat_product_declaration.py
odoo/addons/intrastat_product/models/intrastat_region.py
odoo/addons/intrastat_product/models/intrastat_transaction.py
odoo/addons/intrastat_product/models/intrastat_transport_mode.py
odoo/addons/intrastat_product/models/intrastat_unit.py
odoo/addons/intrastat_product/models/res_company.py
odoo/addons/intrastat_product/models/res_config_settings.py
odoo/addons/intrastat_product/models/res_partner.py
odoo/addons/intrastat_product/models/sale_order.py
odoo/addons/intrastat_product/models/stock_warehouse.py
odoo/addons/intrastat_product/readme/CONFIGURE.rst
odoo/addons/intrastat_product/readme/CONTRIBUTORS.rst
odoo/addons/intrastat_product/readme/DESCRIPTION.rst
odoo/addons/intrastat_product/readme/INSTALL.rst
odoo/addons/intrastat_product/readme/ROADMAP.rst
odoo/addons/intrastat_product/readme/USAGE.rst
odoo/addons/intrastat_product/report/__init__.py
odoo/addons/intrastat_product/report/intrastat_product_report_xls.py
odoo/addons/intrastat_product/security/intrastat_security.xml
odoo/addons/intrastat_product/security/ir.model.access.csv
odoo/addons/intrastat_product/static/description/icon.png
odoo13_addon_intrastat_product-13.0.3.0.4.dist-info/METADATA
odoo13_addon_intrastat_product-13.0.3.0.4.dist-info/WHEEL
odoo13_addon_intrastat_product-13.0.3.0.4.dist-info/top_level.txt
odoo13_addon_intrastat_product-13.0.3.0.4.dist-info/RECORD
