Metadata-Version: 2.1
Name: odoo13-addon-intrastat-product
Version: 13.0.3.0.4
Summary: Base module for Intrastat Product
Home-page: https://github.com/OCA/intrastat-extrastat
Author: brain-tec AG, Akretion, Noviat, Odoo Community Association (OCA)
Author-email: support@odoo-community.org
License: AGPL-3
Platform: UNKNOWN
Classifier: Programming Language :: Python
Classifier: Framework :: Odoo
Classifier: Framework :: Odoo :: 13.0
Classifier: License :: OSI Approved :: GNU Affero General Public License v3
Requires-Python: >=3.5
Requires-Dist: odoo13-addon-intrastat-base
Requires-Dist: odoo13-addon-product-harmonized-system
Requires-Dist: odoo13-addon-report-xlsx-helper
Requires-Dist: odoo (<13.1dev,>=13.0a)
